medlyn2002/__init__.py
medlyn2002/external.py
medlyn2002/info.py
medlyn2002/raw.py
medlyn2002/version.py
medlyn2002/clean/readme.rst
medlyn2002/clean/tab2_arrhenius.csv
medlyn2002/clean/tab2_peaked.csv
medlyn2002/clean/tab3.csv
medlyn2002-1.1.0.dist-info/AUTHORS.rst
medlyn2002-1.1.0.dist-info/LICENSE
medlyn2002-1.1.0.dist-info/METADATA
medlyn2002-1.1.0.dist-info/WHEEL
medlyn2002-1.1.0.dist-info/top_level.txt
medlyn2002-1.1.0.dist-info/RECORD
